{
    "name": "Numb to Slaughter",
    "notes": [
        {
            "type": 60,
            "time": 1.2,
            "position": 9
        },
        {
            "type": 60,
            "time": 1.5999999999999999,
            "position": 9
        },
        {
            "type": 60,
            "time": 1.9999999999999998,
            "position": 9
        },
        {
            "type": 60,
            "time": 2.4,
            "position": 9
        },
        {
            "type": 60,
            "time": 2.8,
            "position": 22
        },
        {
            "type": 60,
            "time": 3.1999999999999997,
            "position": 22
        },
        {
            "type": 60,
            "time": 3.5999999999999996,
            "position": 22
        },
        {
            "type": 60,
            "time": 3.9999999999999996,
            "position": 22
        },
        {
            "type": 60,
            "time": 4.4,
            "position": 30
        },
        {
            "type": 60,
            "time": 4.800000000000001,
            "position": 30
        },
        {
            "type": 60,
            "time": 5.200000000000001,
            "position": 30
        },
        {
            "type": 60,
            "time": 5.600000000000001,
            "position": 30
        },
        {
            "type": 60,
            "time": 6.000000000000002,
            "position": 16
        },
        {
            "type": 60,
            "time": 6.400000000000002,
            "position": 16
        },
        {
            "type": 60,
            "time": 6.8000000000000025,
            "position": 16
        },
        {
            "type": 60,
            "time": 7.200000000000003,
            "position": 16
        },
        {
            "type": 60,
            "time": 7.600000000000003,
            "position": 37
        },
        {
            "type": 60,
            "time": 8.000000000000004,
            "position": 37
        },
        {
            "type": 60,
            "time": 8.400000000000004,
            "position": 37
        },
        {
            "type": 60,
            "time": 8.800000000000004,
            "position": 30
        },
        {
            "type": 60,
            "time": 9.200000000000005,
            "position": 16
        },
        {
            "type": 60,
            "time": 9.600000000000005,
            "position": 16
        },
        {
            "type": 60,
            "time": 10.000000000000005,
            "position": 16
        },
        {
            "type": 60,
            "time": 10.400000000000006,
            "position": 27
        },
        {
            "type": 60,
            "time": 10.800000000000006,
            "position": 5
        },
        {
            "type": 60,
            "time": 11.200000000000006,
            "position": 5
        },
        {
            "type": 60,
            "time": 11.600000000000007,
            "position": 5
        },
        {
            "type": 60,
            "time": 12.000000000000007,
            "position": 5
        },
        {
            "type": 60,
            "time": 12.400000000000007,
            "position": 6
        },
        {
            "type": 60,
            "time": 12.800000000000008,
            "position": 6
        },
        {
            "type": 60,
            "time": 13.200000000000008,
            "position": 6
        },
        {
            "type": 60,
            "time": 13.600000000000009,
            "position": 6
        },
        {
            "type": 60,
            "time": 14.000000000000009,
            "position": 9
        },
        {
            "type": 60,
            "time": 14.40000000000001,
            "position": 9
        },
        {
            "type": 60,
            "time": 14.80000000000001,
            "position": 9
        },
        {
            "type": 60,
            "time": 15.20000000000001,
            "position": 9
        },
        {
            "type": 60,
            "time": 15.60000000000001,
            "position": 32
        },
        {
            "type": 60,
            "time": 16.00000000000001,
            "position": 32
        },
        {
            "type": 60,
            "time": 16.400000000000013,
            "position": 32
        },
        {
            "type": 60,
            "time": 16.800000000000015,
            "position": 32
        },
        {
            "type": 60,
            "time": 17.200000000000017,
            "position": 41
        },
        {
            "type": 60,
            "time": 17.60000000000002,
            "position": 41
        },
        {
            "type": 60,
            "time": 18.00000000000002,
            "position": 41
        },
        {
            "type": 60,
            "time": 18.400000000000023,
            "position": 30
        },
        {
            "type": 60,
            "time": 18.800000000000026,
            "position": 22
        },
        {
            "type": 60,
            "time": 19.200000000000028,
            "position": 22
        },
        {
            "type": 60,
            "time": 19.60000000000003,
            "position": 22
        },
        {
            "type": 60,
            "time": 20.000000000000032,
            "position": 32
        },
        {
            "type": 60,
            "time": 20.20000000000003,
            "position": 22
        },
        {
            "type": 60,
            "time": 20.40000000000003,
            "position": 125
        },
        {
            "type": 60,
            "time": 20.800000000000033,
            "position": 125
        },
        {
            "type": 60,
            "time": 21.200000000000035,
            "position": 125
        },
        {
            "type": 60,
            "time": 21.600000000000037,
            "position": 8
        },
        {
            "type": 60,
            "time": 22.00000000000004,
            "position": 16
        },
        {
            "type": 60,
            "time": 22.40000000000004,
            "position": 16
        },
        {
            "type": 60,
            "time": 22.800000000000043,
            "position": 16
        },
        {
            "type": 60,
            "time": 23.200000000000045,
            "position": 27
        },
        {
            "type": 60,
            "time": 23.600000000000048,
            "position": 5
        },
        {
            "type": 60,
            "time": 24.00000000000005,
            "position": 5
        },
        {
            "type": 60,
            "time": 24.400000000000052,
            "position": 5
        },
        {
            "type": 60,
            "time": 24.800000000000054,
            "position": 5
        },
        {
            "type": 60,
            "time": 25.000000000000053,
            "position": 116
        },
        {
            "type": 60,
            "time": 25.200000000000053,
            "position": 6
        },
        {
            "type": 60,
            "time": 25.600000000000055,
            "position": 6
        },
        {
            "type": 60,
            "time": 26.000000000000057,
            "position": 6
        },
        {
            "type": 60,
            "time": 26.40000000000006,
            "position": 6
        },
        {
            "type": 62,
            "time": 26.80000000000006,
            "position": 9
        },
        {
            "type": 62,
            "time": 27.20000000000006,
            "position": 9
        },
        {
            "type": 62,
            "time": 27.60000000000006,
            "position": 9
        },
        {
            "type": 62,
            "time": 28.000000000000057,
            "position": 9
        },
        {
            "type": 62,
            "time": 28.400000000000055,
            "position": 14
        },
        {
            "type": 62,
            "time": 28.800000000000054,
            "position": 14
        },
        {
            "type": 62,
            "time": 29.200000000000053,
            "position": 14
        },
        {
            "type": 62,
            "time": 30.00000000000005,
            "position": 24
        },
        {
            "type": 62,
            "time": 30.40000000000005,
            "position": 24
        },
        {
            "type": 62,
            "time": 30.800000000000047,
            "position": 24
        },
        {
            "type": 62,
            "time": 31.200000000000045,
            "position": 24
        },
        {
            "type": 62,
            "time": 31.600000000000044,
            "position": 19
        },
        {
            "type": 62,
            "time": 32.00000000000004,
            "position": 19
        },
        {
            "type": 62,
            "time": 32.40000000000005,
            "position": 19
        },
        {
            "type": 62,
            "time": 33.20000000000005,
            "position": 34
        },
        {
            "type": 62,
            "time": 33.60000000000006,
            "position": 34
        },
        {
            "type": 62,
            "time": 34.000000000000064,
            "position": 34
        },
        {
            "type": 62,
            "time": 34.40000000000007,
            "position": 24
        },
        {
            "type": 62,
            "time": 34.800000000000075,
            "position": 19
        },
        {
            "type": 62,
            "time": 35.20000000000008,
            "position": 19
        },
        {
            "type": 62,
            "time": 35.60000000000009,
            "position": 19
        },
        {
            "type": 62,
            "time": 36.00000000000009,
            "position": 24
        },
        {
            "type": 62,
            "time": 36.4000000000001,
            "position": 14
        },
        {
            "type": 62,
            "time": 36.800000000000104,
            "position": 14
        },
        {
            "type": 62,
            "time": 37.20000000000011,
            "position": 14
        },
        {
            "type": 62,
            "time": 37.600000000000115,
            "position": 14
        },
        {
            "type": 60,
            "time": 38.00000000000012,
            "position": 5
        },
        {
            "type": 60,
            "time": 38.10000000000012,
            "position": 6
        },
        {
            "type": 60,
            "time": 38.200000000000124,
            "position": 7
        },
        {
            "type": 60,
            "time": 38.300000000000125,
            "position": 8
        },
        {
            "type": 60,
            "time": 38.50000000000013,
            "position": 10
        },
        {
            "type": 60,
            "time": 38.70000000000013,
            "position": 12
        },
        {
            "type": 60,
            "time": 38.80000000000013,
            "position": 13
        },
        {
            "type": 60,
            "time": 38.900000000000134,
            "position": 14
        },
        {
            "type": 60,
            "time": 39.000000000000135,
            "position": 15
        },
        {
            "type": 60,
            "time": 39.30000000000014,
            "position": 18
        },
        {
            "type": 60,
            "time": 39.40000000000014,
            "position": 19
        },
        {
            "type": 59,
            "time": 39.60000000000014,
            "position": 9,
            "duration": 3.4285679999999985
        },
        {
            "type": 59,
            "time": 43.02856800000014,
            "position": 44,
            "duration": 3.411603731249997
        },
        {
            "type": 59,
            "time": 46.45713600000014,
            "position": 26,
            "duration": 3.411603731249997
        },
        {
            "type": 59,
            "time": 49.88570400000014,
            "position": 59,
            "duration": 1.7142839999999993
        },
        {
            "type": 59,
            "time": 51.59998800000014,
            "position": 26,
            "duration": 1.7142839999999993
        },
        {
            "type": 58,
            "time": 53.31427200000014,
            "position": 103,
            "duration": 3.4285679999999985
        },
        {
            "type": 58,
            "time": 56.742840000000136,
            "position": 95,
            "duration": 3.4285679999999985
        },
        {
            "type": 58,
            "time": 60.171408000000135,
            "position": 6,
            "duration": 2.5714260000000024
        },
        {
            "type": 58,
            "time": 62.74283400000014,
            "position": 16,
            "duration": 0.8571420000000032
        },
        {
            "type": 58,
            "time": 63.59997600000014,
            "position": 38,
            "duration": 1.7142840000000064
        },
        {
            "type": 58,
            "time": 65.31426000000015,
            "position": 46,
            "duration": 1.7142840000000064
        },
        {
            "type": 60,
            "time": 67.02854400000015,
            "position": 30
        },
        {
            "type": 60,
            "time": 67.24282950000016,
            "position": 30
        },
        {
            "type": 60,
            "time": 67.56425775000015,
            "position": 30
        },
        {
            "type": 60,
            "time": 67.88568600000015,
            "position": 30
        },
        {
            "type": 60,
            "time": 67.99282875000016,
            "position": 30
        },
        {
            "type": 60,
            "time": 68.42139975000016,
            "position": 30
        },
        {
            "type": 60,
            "time": 68.74282800000016,
            "position": 4
        },
        {
            "type": 60,
            "time": 68.95711350000016,
            "position": 127
        },
        {
            "type": 60,
            "time": 69.27854175000016,
            "position": 121
        },
        {
            "type": 60,
            "time": 69.59997000000016,
            "position": 115
        },
        {
            "type": 60,
            "time": 69.70711275000016,
            "position": 113
        },
        {
            "type": 60,
            "time": 70.13568375000017,
            "position": 105
        },
        {
            "type": 60,
            "time": 70.45711200000017,
            "position": 105
        },
        {
            "type": 60,
            "time": 70.67139750000017,
            "position": 114
        },
        {
            "type": 60,
            "time": 70.99282575000016,
            "position": 0
        },
        {
            "type": 60,
            "time": 71.31425400000016,
            "position": 13
        },
        {
            "type": 60,
            "time": 71.42139675000017,
            "position": 18
        },
        {
            "type": 60,
            "time": 71.84996775000018,
            "position": 37
        },
        {
            "type": 60,
            "time": 72.17139600000017,
            "position": 37
        },
        {
            "type": 60,
            "time": 72.38568150000017,
            "position": 37
        },
        {
            "type": 60,
            "time": 72.70710975000017,
            "position": 37
        },
        {
            "type": 60,
            "time": 73.02853800000017,
            "position": 37
        },
        {
            "type": 60,
            "time": 73.13568075000018,
            "position": 37
        },
        {
            "type": 60,
            "time": 73.56425175000018,
            "position": 37
        },
        {
            "type": 60,
            "time": 73.88568000000018,
            "position": 10
        },
        {
            "type": 60,
            "time": 74.09996550000018,
            "position": 10
        },
        {
            "type": 60,
            "time": 74.42139375000018,
            "position": 10
        },
        {
            "type": 60,
            "time": 74.74282200000017,
            "position": 10
        },
        {
            "type": 60,
            "time": 74.84996475000018,
            "position": 10
        },
        {
            "type": 60,
            "time": 75.27853575000019,
            "position": 10
        },
        {
            "type": 60,
            "time": 75.59996400000018,
            "position": 114
        },
        {
            "type": 60,
            "time": 75.81424950000019,
            "position": 114
        },
        {
            "type": 60,
            "time": 76.13567775000018,
            "position": 114
        },
        {
            "type": 60,
            "time": 76.45710600000018,
            "position": 114
        },
        {
            "type": 60,
            "time": 76.56424875000019,
            "position": 114
        },
        {
            "type": 60,
            "time": 76.9928197500002,
            "position": 114
        },
        {
            "type": 60,
            "time": 77.31424800000019,
            "position": 8
        },
        {
            "type": 60,
            "time": 77.5285335000002,
            "position": 8
        },
        {
            "type": 60,
            "time": 77.84996175000019,
            "position": 8
        },
        {
            "type": 60,
            "time": 78.17139000000019,
            "position": 8
        },
        {
            "type": 60,
            "time": 78.2785327500002,
            "position": 8
        },
        {
            "type": 60,
            "time": 78.7071037500002,
            "position": 8
        },
        {
            "type": 60,
            "time": 79.0285320000002,
            "position": 78
        },
        {
            "type": 60,
            "time": 79.2428175000002,
            "position": 78
        },
        {
            "type": 60,
            "time": 79.5642457500002,
            "position": 78
        },
        {
            "type": 60,
            "time": 79.8856740000002,
            "position": 78
        },
        {
            "type": 60,
            "time": 79.9928167500002,
            "position": 78
        },
        {
            "type": 60,
            "time": 80.4213877500002,
            "position": 78
        },
        {
            "type": 60,
            "time": 80.7428160000002,
            "position": 5
        },
        {
            "type": 60,
            "time": 80.84995875000021,
            "position": 6
        },
        {
            "type": 60,
            "time": 80.95710150000022,
            "position": 7
        },
        {
            "type": 60,
            "time": 81.06424425000023,
            "position": 8
        },
        {
            "type": 60,
            "time": 81.27852975000023,
            "position": 10
        },
        {
            "type": 60,
            "time": 81.49281525000023,
            "position": 12
        },
        {
            "type": 60,
            "time": 81.59995800000024,
            "position": 13
        },
        {
            "type": 60,
            "time": 81.70710075000025,
            "position": 14
        },
        {
            "type": 60,
            "time": 81.81424350000026,
            "position": 15
        },
        {
            "type": 60,
            "time": 82.13567175000026,
            "position": 18
        },
        {
            "type": 60,
            "time": 82.24281450000026,
            "position": 19
        },
        {
            "type": 60,
            "time": 82.45710000000027,
            "position": 124
        },
        {
            "type": 60,
            "time": 82.56424275000028,
            "position": 121
        },
        {
            "type": 60,
            "time": 82.67138550000028,
            "position": 119
        },
        {
            "type": 60,
            "time": 82.77852825000029,
            "position": 116
        },
        {
            "type": 60,
            "time": 82.9928137500003,
            "position": 111
        },
        {
            "type": 60,
            "time": 83.2070992500003,
            "position": 106
        },
        {
            "type": 60,
            "time": 83.3142420000003,
            "position": 104
        },
        {
            "type": 60,
            "time": 83.42138475000031,
            "position": 101
        },
        {
            "type": 60,
            "time": 83.52852750000032,
            "position": 99
        },
        {
            "type": 60,
            "time": 83.84995575000032,
            "position": 91
        },
        {
            "type": 60,
            "time": 83.95709850000033,
            "position": 89
        },
        {
            "type": 60,
            "time": 84.17138400000033,
            "position": 113
        },
        {
            "type": 60,
            "time": 84.27852675000034,
            "position": 117
        },
        {
            "type": 60,
            "time": 84.38566950000035,
            "position": 120
        },
        {
            "type": 60,
            "time": 84.49281225000036,
            "position": 124
        },
        {
            "type": 60,
            "time": 84.70709775000036,
            "position": 3
        },
        {
            "type": 60,
            "time": 84.92138325000036,
            "position": 11
        },
        {
            "type": 60,
            "time": 85.02852600000037,
            "position": 15
        },
        {
            "type": 60,
            "time": 85.13566875000038,
            "position": 18
        },
        {
            "type": 60,
            "time": 85.24281150000039,
            "position": 22
        },
        {
            "type": 60,
            "time": 85.56423975000038,
            "position": 33
        },
        {
            "type": 60,
            "time": 85.67138250000039,
            "position": 37
        },
        {
            "type": 60,
            "time": 85.8856680000004,
            "position": 43
        },
        {
            "type": 60,
            "time": 85.9928107500004,
            "position": 43
        },
        {
            "type": 60,
            "time": 86.09995350000041,
            "position": 43
        },
        {
            "type": 60,
            "time": 86.20709625000042,
            "position": 43
        },
        {
            "type": 60,
            "time": 86.42138175000042,
            "position": 43
        },
        {
            "type": 60,
            "time": 86.63566725000042,
            "position": 43
        },
        {
            "type": 60,
            "time": 86.74281000000043,
            "position": 43
        },
        {
            "type": 60,
            "time": 86.84995275000044,
            "position": 43
        },
        {
            "type": 60,
            "time": 86.95709550000045,
            "position": 43
        },
        {
            "type": 60,
            "time": 87.27852375000045,
            "position": 43
        },
        {
            "type": 60,
            "time": 87.38566650000045,
            "position": 43
        },
        {
            "type": 60,
            "time": 87.59995200000046,
            "position": 49
        },
        {
            "type": 60,
            "time": 87.70709475000046,
            "position": 46
        },
        {
            "type": 60,
            "time": 87.81423750000047,
            "position": 44
        },
        {
            "type": 60,
            "time": 87.92138025000048,
            "position": 41
        },
        {
            "type": 60,
            "time": 88.13566575000048,
            "position": 36
        },
        {
            "type": 60,
            "time": 88.34995125000049,
            "position": 31
        },
        {
            "type": 60,
            "time": 88.4570940000005,
            "position": 28
        },
        {
            "type": 60,
            "time": 88.5642367500005,
            "position": 26
        },
        {
            "type": 60,
            "time": 88.67137950000051,
            "position": 23
        },
        {
            "type": 60,
            "time": 88.99280775000051,
            "position": 16
        },
        {
            "type": 60,
            "time": 89.09995050000052,
            "position": 13
        },
        {
            "type": 60,
            "time": 89.31423600000052,
            "position": 5
        },
        {
            "type": 60,
            "time": 89.42137875000053,
            "position": 6
        },
        {
            "type": 60,
            "time": 89.52852150000054,
            "position": 7
        },
        {
            "type": 60,
            "time": 89.63566425000054,
            "position": 8
        },
        {
            "type": 60,
            "time": 89.84994975000055,
            "position": 10
        },
        {
            "type": 60,
            "time": 90.06423525000055,
            "position": 12
        },
        {
            "type": 60,
            "time": 90.17137800000056,
            "position": 13
        },
        {
            "type": 60,
            "time": 90.27852075000057,
            "position": 14
        },
        {
            "type": 60,
            "time": 90.38566350000058,
            "position": 15
        },
        {
            "type": 60,
            "time": 90.70709175000057,
            "position": 18
        },
        {
            "type": 60,
            "time": 90.81423450000058,
            "position": 19
        },
        {
            "type": 60,
            "time": 91.02852000000058,
            "position": 112
        },
        {
            "type": 60,
            "time": 91.13566275000059,
            "position": 112
        },
        {
            "type": 60,
            "time": 91.2428055000006,
            "position": 112
        },
        {
            "type": 60,
            "time": 91.34994825000061,
            "position": 112
        },
        {
            "type": 60,
            "time": 91.56423375000061,
            "position": 112
        },
        {
            "type": 60,
            "time": 91.77851925000061,
            "position": 112
        },
        {
            "type": 60,
            "time": 91.88566200000062,
            "position": 112
        },
        {
            "type": 60,
            "time": 91.99280475000063,
            "position": 112
        },
        {
            "type": 60,
            "time": 92.09994750000064,
            "position": 112
        },
        {
            "type": 60,
            "time": 92.42137575000064,
            "position": 112
        },
        {
            "type": 60,
            "time": 92.52851850000064,
            "position": 112
        },
        {
            "type": 60,
            "time": 92.74280400000065,
            "position": 26
        },
        {
            "type": 60,
            "time": 92.84994675000065,
            "position": 23
        },
        {
            "type": 60,
            "time": 92.95708950000066,
            "position": 20
        },
        {
            "type": 60,
            "time": 93.06423225000067,
            "position": 17
        },
        {
            "type": 60,
            "time": 93.27851775000067,
            "position": 11
        },
        {
            "type": 60,
            "time": 93.49280325000068,
            "position": 5
        },
        {
            "type": 60,
            "time": 93.59994600000068,
            "position": 2
        },
        {
            "type": 60,
            "time": 93.7070887500007,
            "position": 127
        },
        {
            "type": 60,
            "time": 93.8142315000007,
            "position": 124
        },
        {
            "type": 60,
            "time": 94.1356597500007,
            "position": 115
        },
        {
            "type": 60,
            "time": 94.2428025000007,
            "position": 112
        },
        {
            "type": 59,
            "time": 94.45708800000071,
            "position": 40,
            "duration": 2.653125000000003
        },
        {
            "type": 60,
            "time": 97.44771300000072,
            "position": 16
        },
        {
            "type": 60,
            "time": 97.82792133333405,
            "position": 31
        },
        {
            "type": 60,
            "time": 98.19354633333404,
            "position": 46
        },
        {
            "type": 60,
            "time": 98.45708800000071,
            "position": 32
        },
        {
            "type": 60,
            "time": 98.93417133333405,
            "position": 27
        },
        {
            "type": 58,
            "time": 99.20708800000072,
            "position": 11,
            "duration": 2.72604166666666
        },
        {
            "type": 60,
            "time": 101.92896300000072,
            "position": 120
        },
        {
            "type": 59,
            "time": 102.45708800000071,
            "position": 19,
            "duration": 2.698958333333337
        },
        {
            "type": 60,
            "time": 105.43937966666738,
            "position": 17
        },
        {
            "type": 60,
            "time": 105.82375466666738,
            "position": 29
        },
        {
            "type": 60,
            "time": 106.19667133333405,
            "position": 43
        },
        {
            "type": 60,
            "time": 106.45708800000072,
            "position": 35
        },
        {
            "type": 60,
            "time": 106.95708800000072,
            "position": 46
        },
        {
            "type": 58,
            "time": 107.20708800000072,
            "position": 24,
            "duration": 2.1937499999999943
        },
        {
            "type": 60,
            "time": 109.44250466666739,
            "position": 36
        },
        {
            "type": 60,
            "time": 109.66958800000073,
            "position": 43
        },
        {
            "type": 60,
            "time": 109.9362546666674,
            "position": 52
        },
        {
            "type": 58,
            "time": 110.45708800000074,
            "position": 59,
            "duration": 1.9583333333333286
        },
        {
            "type": 58,
            "time": 112.45708800000074,
            "position": 25,
            "duration": 1.4166666666666714
        },
        {
            "type": 60,
            "time": 113.95708800000074,
            "position": 36
        },
        {
            "type": 58,
            "time": 114.45708800000074,
            "position": 21,
            "duration": 2.0
        },
        {
            "type": 60,
            "time": 116.82479633333408,
            "position": 120
        },
        {
            "type": 60,
            "time": 117.19146300000074,
            "position": 115
        },
        {
            "type": 60,
            "time": 117.45708800000074,
            "position": 111
        },
        {
            "type": 60,
            "time": 117.76958800000074,
            "position": 107
        },
        {
            "type": 60,
            "time": 118.08208800000074,
            "position": 1
        },
        {
            "type": 60,
            "time": 118.4706296666674,
            "position": 16
        },
        {
            "type": 59,
            "time": 118.88104633333407,
            "position": 23,
            "duration": 1.566666666666677
        },
        {
            "type": 60,
            "time": 120.46542133333408,
            "position": 43
        },
        {
            "type": 60,
            "time": 120.82271300000075,
            "position": 26
        },
        {
            "type": 60,
            "time": 121.17167133333407,
            "position": 10
        },
        {
            "type": 60,
            "time": 121.46021300000075,
            "position": 124
        },
        {
            "type": 60,
            "time": 121.81437966666742,
            "position": 112
        },
        {
            "type": 60,
            "time": 122.11958800000076,
            "position": 98
        },
        {
            "type": 60,
            "time": 122.45708800000077,
            "position": 87
        },
        {
            "type": 60,
            "time": 122.52896300000077,
            "position": 89
        },
        {
            "type": 60,
            "time": 122.63833800000077,
            "position": 92
        },
        {
            "type": 60,
            "time": 122.70396300000077,
            "position": 94
        },
        {
            "type": 60,
            "time": 122.77271300000076,
            "position": 96
        },
        {
            "type": 60,
            "time": 122.8404213333341,
            "position": 98
        },
        {
            "type": 60,
            "time": 122.95812966666745,
            "position": 101
        },
        {
            "type": 58,
            "time": 123.08208800000078,
            "position": 105,
            "duration": 1.3447916666666657
        },
        {
            "type": 59,
            "time": 124.47792133333411,
            "position": 11,
            "duration": 0.9479166666666714
        },
        {
            "type": 60,
            "time": 125.45708800000078,
            "position": 32
        },
        {
            "type": 60,
            "time": 125.95708800000078,
            "position": 55
        },
        {
            "type": 60,
            "time": 126.20708800000078,
            "position": 49
        },
        {
            "type": 60,
            "time": 126.45708800000078,
            "position": 9
        },
        {
            "type": 60,
            "time": 126.83208800000078,
            "position": 9
        },
        {
            "type": 60,
            "time": 127.20708800000078,
            "position": 9
        },
        {
            "type": 60,
            "time": 127.58208800000078,
            "position": 9
        },
        {
            "type": 60,
            "time": 127.95708800000078,
            "position": 22
        },
        {
            "type": 60,
            "time": 128.3320880000008,
            "position": 22
        },
        {
            "type": 60,
            "time": 128.7070880000008,
            "position": 22
        },
        {
            "type": 60,
            "time": 129.0820880000008,
            "position": 22
        },
        {
            "type": 60,
            "time": 129.4570880000008,
            "position": 30
        },
        {
            "type": 60,
            "time": 129.8320880000008,
            "position": 30
        },
        {
            "type": 60,
            "time": 130.2070880000008,
            "position": 30
        },
        {
            "type": 60,
            "time": 130.5820880000008,
            "position": 30
        },
        {
            "type": 60,
            "time": 130.9570880000008,
            "position": 16
        },
        {
            "type": 60,
            "time": 131.3320880000008,
            "position": 16
        },
        {
            "type": 60,
            "time": 131.7070880000008,
            "position": 16
        },
        {
            "type": 60,
            "time": 132.0820880000008,
            "position": 16
        },
        {
            "type": 60,
            "time": 132.4570880000008,
            "position": 37
        },
        {
            "type": 60,
            "time": 132.8320880000008,
            "position": 37
        },
        {
            "type": 60,
            "time": 133.2070880000008,
            "position": 37
        },
        {
            "type": 60,
            "time": 133.5820880000008,
            "position": 30
        },
        {
            "type": 60,
            "time": 133.9570880000008,
            "position": 16
        },
        {
            "type": 60,
            "time": 134.3320880000008,
            "position": 16
        },
        {
            "type": 60,
            "time": 134.7070880000008,
            "position": 16
        },
        {
            "type": 60,
            "time": 135.0820880000008,
            "position": 27
        },
        {
            "type": 60,
            "time": 135.4570880000008,
            "position": 5
        },
        {
            "type": 60,
            "time": 135.8320880000008,
            "position": 5
        },
        {
            "type": 60,
            "time": 136.2070880000008,
            "position": 5
        },
        {
            "type": 60,
            "time": 136.5820880000008,
            "position": 5
        },
        {
            "type": 60,
            "time": 136.9570880000008,
            "position": 6
        },
        {
            "type": 60,
            "time": 137.3320880000008,
            "position": 6
        },
        {
            "type": 60,
            "time": 137.7070880000008,
            "position": 6
        },
        {
            "type": 60,
            "time": 138.0820880000008,
            "position": 6
        },
        {
            "type": 60,
            "time": 138.4570880000008,
            "position": 9
        },
        {
            "type": 60,
            "time": 138.8320880000008,
            "position": 9
        },
        {
            "type": 60,
            "time": 139.2070880000008,
            "position": 9
        },
        {
            "type": 60,
            "time": 139.5820880000008,
            "position": 9
        },
        {
            "type": 60,
            "time": 139.9570880000008,
            "position": 32
        },
        {
            "type": 60,
            "time": 140.3320880000008,
            "position": 32
        },
        {
            "type": 60,
            "time": 140.7070880000008,
            "position": 32
        },
        {
            "type": 60,
            "time": 141.0820880000008,
            "position": 32
        },
        {
            "type": 60,
            "time": 141.4570880000008,
            "position": 41
        },
        {
            "type": 60,
            "time": 141.8320880000008,
            "position": 41
        },
        {
            "type": 60,
            "time": 142.2070880000008,
            "position": 41
        },
        {
            "type": 60,
            "time": 142.5820880000008,
            "position": 30
        },
        {
            "type": 60,
            "time": 142.9570880000008,
            "position": 22
        },
        {
            "type": 60,
            "time": 143.3320880000008,
            "position": 22
        },
        {
            "type": 60,
            "time": 143.7070880000008,
            "position": 22
        },
        {
            "type": 60,
            "time": 144.0820880000008,
            "position": 32
        },
        {
            "type": 60,
            "time": 144.2695880000008,
            "position": 22
        },
        {
            "type": 60,
            "time": 144.4570880000008,
            "position": 125
        },
        {
            "type": 60,
            "time": 144.8320880000008,
            "position": 125
        },
        {
            "type": 60,
            "time": 145.2070880000008,
            "position": 125
        },
        {
            "type": 60,
            "time": 145.5820880000008,
            "position": 8
        },
        {
            "type": 60,
            "time": 145.9570880000008,
            "position": 16
        },
        {
            "type": 60,
            "time": 146.3320880000008,
            "position": 16
        },
        {
            "type": 60,
            "time": 146.7070880000008,
            "position": 16
        },
        {
            "type": 60,
            "time": 147.0820880000008,
            "position": 27
        },
        {
            "type": 60,
            "time": 147.4570880000008,
            "position": 5
        },
        {
            "type": 60,
            "time": 147.8320880000008,
            "position": 5
        },
        {
            "type": 60,
            "time": 148.2070880000008,
            "position": 5
        },
        {
            "type": 60,
            "time": 148.5820880000008,
            "position": 5
        },
        {
            "type": 60,
            "time": 148.7695880000008,
            "position": 116
        },
        {
            "type": 60,
            "time": 148.9570880000008,
            "position": 6
        },
        {
            "type": 60,
            "time": 149.3320880000008,
            "position": 6
        },
        {
            "type": 60,
            "time": 149.7070880000008,
            "position": 6
        },
        {
            "type": 60,
            "time": 150.0820880000008,
            "position": 6
        }
    ]
}
